universal_annotator/.git/COMMIT_EDITMSG
universal_annotator/.git/HEAD
universal_annotator/.git/config
universal_annotator/.git/description
universal_annotator/.git/hooks/applypatch-msg.sample
universal_annotator/.git/hooks/commit-msg.sample
universal_annotator/.git/hooks/fsmonitor-watchman.sample
universal_annotator/.git/hooks/post-update.sample
universal_annotator/.git/hooks/pre-applypatch.sample
universal_annotator/.git/hooks/pre-commit.sample
universal_annotator/.git/hooks/pre-merge-commit.sample
universal_annotator/.git/hooks/pre-push.sample
universal_annotator/.git/hooks/pre-rebase.sample
universal_annotator/.git/hooks/pre-receive.sample
universal_annotator/.git/hooks/prepare-commit-msg.sample
universal_annotator/.git/hooks/push-to-checkout.sample
universal_annotator/.git/hooks/sendemail-validate.sample
universal_annotator/.git/hooks/update.sample
universal_annotator/.git/index
universal_annotator/.git/info/exclude
universal_annotator/.git/logs/HEAD
universal_annotator/.git/logs/refs/heads/main
universal_annotator/.git/logs/refs/remotes/origin/main
universal_annotator/.git/objects/00/6c7253ee777409157589c95c4a5c3d72dda044
universal_annotator/.git/objects/02/961291de07b6677fa96091e66f7c8eb61ba74d
universal_annotator/.git/objects/03/00035ebf58be5a68f9aa0b394da8097c7fa4d3
universal_annotator/.git/objects/03/0e87cb43b9baa8acfd3eb9a9011f2b3f0f31eb
universal_annotator/.git/objects/03/3ebf5b3db0d1c6402bb128a69af6bd7ec73689
universal_annotator/.git/objects/06/1738d1911f1affd02043763a6b23ea5ea88882
universal_annotator/.git/objects/06/ec1bf975aa8e688d93e5534a6507a4c852318d
universal_annotator/.git/objects/07/12c30db8360571fbe3bdbf5adc68e6e42e7e5d
universal_annotator/.git/objects/07/b9ea0edd733ab55c790c74894f4d1268574c03
universal_annotator/.git/objects/08/bb923ab06080206b0e89c7f7b1552bc593b0c5
universal_annotator/.git/objects/09/d7a6b4b361f31a2e148ab14dbb3bf32267ab34
universal_annotator/.git/objects/0a/6e4ae2d71b91b2e9655688e466d1d2e9736759
universal_annotator/universal_annotator.egg-info/PKG-INFO
universal_annotator/universal_annotator.egg-info/SOURCES.txt
universal_annotator/universal_annotator.egg-info/dependency_links.txt
universal_annotator/universal_annotator.egg-info/entry_points.txt
universal_annotator/universal_annotator.egg-info/requires.txt
universal_annotator/universal_annotator.egg-info/top_level.txt
universal_annotator-0.1.7.dist-info/WHEEL
universal_annotator-0.1.7.dist-info/entry_points.txt
universal_annotator-0.1.7.dist-info/METADATA
universal_annotator-0.1.7.dist-info/RECORD
