Metadata-Version: 2.3
Name: universal-annotator
Version: 0.1.7
Summary: Universal Annotation Tool for images
Author: Madan Mohan
Author-email: Madan Mohan <madanmmj3@gmail.com>
License:                                   LICENSE
Requires-Dist: pyqt5>=5.15
Requires-Dist: pyqt5-sip>=12.11
Requires-Dist: pillow>=9.0
Requires-Dist: opencv-python>=4.5
Requires-Dist: numpy>=1.20
Requires-Dist: tqdm>=4.60
Requires-Dist: pyyaml>=6.0
Requires-Dist: jsonschema>=4.0
Requires-Python: >=3.12
